source_google_sheets/__init__.py
source_google_sheets/components/__init__.py
source_google_sheets/components/extractors.py
source_google_sheets/components/partition_routers.py
source_google_sheets/manifest.yaml
source_google_sheets/models/__init__.py
source_google_sheets/models/spreadsheet.py
source_google_sheets/models/spreadsheet_values.py
source_google_sheets/run.py
source_google_sheets/source.py
source_google_sheets/spec.yaml
source_google_sheets/utils.py
airbyte_source_google_sheets-0.11.0.dist-info/METADATA
airbyte_source_google_sheets-0.11.0.dist-info/WHEEL
airbyte_source_google_sheets-0.11.0.dist-info/entry_points.txt
airbyte_source_google_sheets-0.11.0.dist-info/RECORD
