Metadata-Version: 2.3
Name: airbyte-source-google-sheets
Version: 0.11.0
Summary: Source implementation for Google Sheets.
License: Elv2
Author: Airbyte
Author-email: contact@airbyte.io
Requires-Python: >=3.10,<3.13
Classifier: License :: Other/Proprietary License
Classifier: Programming Language :: Python :: 3
Classifier: Programming Language :: Python :: 3.10
Classifier: Programming Language :: Python :: 3.11
Classifier: Programming Language :: Python :: 3.12
Requires-Dist: airbyte-cdk (>=6,<7)
Project-URL: Documentation, https://docs.airbyte.com/integrations/sources/google-sheets
Project-URL: Homepage, https://airbyte.com
Project-URL: Repository, https://github.com/airbytehq/airbyte
